odoo10_addon_base_partner_sequence-10.0.1.0.0-py2.7-nspkg.pth
odoo10_addon_base_partner_sequence-10.0.1.0.0.dist-info/top_level.txt
odoo10_addon_base_partner_sequence-10.0.1.0.0.dist-info/WHEEL
odoo10_addon_base_partner_sequence-10.0.1.0.0.dist-info/RECORD
odoo10_addon_base_partner_sequence-10.0.1.0.0.dist-info/metadata.json
odoo10_addon_base_partner_sequence-10.0.1.0.0.dist-info/DESCRIPTION.rst
odoo10_addon_base_partner_sequence-10.0.1.0.0.dist-info/METADATA
odoo10_addon_base_partner_sequence-10.0.1.0.0.dist-info/namespace_packages.txt
odoo/addons/base_partner_sequence/__manifest__.py
odoo/addons/base_partner_sequence/__init__.py
odoo/addons/base_partner_sequence/README.rst
odoo/addons/base_partner_sequence/models/partner.py
odoo/addons/base_partner_sequence/models/__init__.py
odoo/addons/base_partner_sequence/i18n/it.po
odoo/addons/base_partner_sequence/i18n/es.po
odoo/addons/base_partner_sequence/i18n/sl.po
odoo/addons/base_partner_sequence/i18n/nl.po
odoo/addons/base_partner_sequence/i18n/de.po
odoo/addons/base_partner_sequence/i18n/fr.po
odoo/addons/base_partner_sequence/i18n/pt_BR.po
odoo/addons/base_partner_sequence/i18n/fi.po
odoo/addons/base_partner_sequence/views/partner_view.xml
odoo/addons/base_partner_sequence/data/partner_sequence.xml
odoo/addons/base_partner_sequence/tests/test_base_partner_sequence.py
odoo/addons/base_partner_sequence/tests/__init__.py
odoo/addons/base_partner_sequence/static/description/icon.png
