Metadata-Version: 2.0
Name: odoo10-addon-base-partner-sequence
Version: 10.0.1.0.0
Summary: Sets customer's code from a sequence
Home-page: http://www.initos.com
Author: Tiny/initOS GmbH & Co. KG,ACSONE SA/NV,Tecnativa, Odoo Community Association (OCA), Camptocamp, 
Author-email: support@odoo-community.org
License: AGPL-3
Platform: UNKNOWN
Requires-Dist: odoo (<10.1dev,>=10.0)
Classifier: Programming Language :: Python :: 2.7
Classifier: Framework :: Odoo
Classifier: License :: OSI Approved :: GNU Affero General Public License v3
